jovsatools/__init__.py
jovsatools/_nbdev.py
jovsatools/custom_pytorch_training.py
jovsatools/custom_tf_training.py
jovsatools/customizing_tf_fit.py
jovsatools/data_generator.py
jovsatools/design_doc.py
jovsatools/dice_experiments.py
jovsatools/function_approximation.py
jovsatools/gdrive_activity_tracking.py
jovsatools/google_activity_tracking.py
jovsatools/google_drive_activity_tracking.py
jovsatools/kelly_criterion.py
jovsatools/sample_mesa.py
jovsatools/transformers.py
notebooks/__init__.py
jovsatools-0.0.8.dist-info/LICENSE
jovsatools-0.0.8.dist-info/METADATA
jovsatools-0.0.8.dist-info/WHEEL
jovsatools-0.0.8.dist-info/entry_points.txt
jovsatools-0.0.8.dist-info/top_level.txt
jovsatools-0.0.8.dist-info/RECORD
