Metadata-Version: 2.1
Name: jovsatools
Version: 0.0.8
Summary: A collection of tools
Home-page: https://github.com/jovsa/jovsatools
Author: Jovan Sardinha
Author-email: jovan.sardinha@gmail.com
License: Apache Software License 2.0
Keywords: tools for jovsa
Platform: UNKNOWN
Classifier: Development Status :: 3 - Alpha
Classifier: Intended Audience :: Developers
Classifier: License :: OSI Approved :: Apache Software License
Classifier: Natural Language :: English
Classifier: Programming Language :: Python :: 3.6
Classifier: Programming Language :: Python :: 3.7
Classifier: Programming Language :: Python :: 3.8
Requires-Python: >=3.6
Requires-Dist: black
Requires-Dist: fastcore
Requires-Dist: flake8
Requires-Dist: google-api-python-client
Requires-Dist: google-auth-httplib2
Requires-Dist: google-auth-oauthlib
Requires-Dist: graphviz
Requires-Dist: ipdb
Requires-Dist: ipywidgets
Requires-Dist: jupyter
Requires-Dist: matplotlib
Requires-Dist: mesa
Requires-Dist: numpy
Requires-Dist: nbdev
Requires-Dist: pandas
Requires-Dist: pydot
Requires-Dist: pydotplus
Requires-Dist: seaborn
Requires-Dist: sklearn
Requires-Dist: sympy
Requires-Dist: tensorflow (>=2.2.0)
Requires-Dist: tensorflow-datasets
Requires-Dist: torch
Requires-Dist: torchvision
Requires-Dist: tqdm
Requires-Dist: twine
